pkgsize/__init__.py
pkgsize/_venv_inspector.py
pkgsize/cli.py
pkgsize/core.py
pypkgsize-1.0.1.dist-info/licenses/LICENSE
pypkgsize-1.0.1.dist-info/METADATA
pypkgsize-1.0.1.dist-info/WHEEL
pypkgsize-1.0.1.dist-info/entry_points.txt
pypkgsize-1.0.1.dist-info/top_level.txt
pypkgsize-1.0.1.dist-info/RECORD
