Metadata-Version: 2.4
Name: pypkgsize
Version: 1.0.1
Summary: A Python package to analyze the disk usage of installed packages.
Author-email: Duc Nguyen <minhducng.dev@gmail.com>
License-Expression: MIT
Project-URL: Homepage, https://github.com/crkacer/pypkgsize
Project-URL: Bug Tracker, https://github.com/crkacer/pypkgsize/issues
Classifier: Programming Language :: Python :: 3
Classifier: Operating System :: OS Independent
Classifier: Environment :: Console
Classifier: Topic :: System :: Filesystems
Classifier: Topic :: Utilities
Requires-Python: >=3.7
License-File: LICENSE
Requires-Dist: click>=8.0
Requires-Dist: packaging
Provides-Extra: test
Requires-Dist: pytest; extra == "test"
Requires-Dist: pytest-mock; extra == "test"
Dynamic: license-file
